[
  {
    "id": "8a846f48-4c21-427b-b8b7-802429af0735",
    "name": "1: RAVANESHWARAM",
    "has_children": false,
    "type": "ward"
  },
  {
    "id": "11d47b58-c11d-4036-9877-37d8c65fa90a",
    "name": "2: RAMAGIRI",
    "has_children": false,
    "type": "ward"
  },
  {
    "id": "8da77fbd-cf8f-4d08-a85d-c6e4f9fb9385",
    "name": "3: VELASHWARAM",
    "has_children": false,
    "type": "ward"
  },
  {
    "id": "b38242f6-41b7-4f69-aff8-96917288da1f",
    "name": "4: MADIYAN",
    "has_children": false,
    "type": "ward"
  },
  {
    "id": "44d598e1-a746-478b-9890-3bbd17351a3a",
    "name": "5: MANIKOTH",
    "has_children": false,
    "type": "ward"
  },
  {
    "id": "f5ea5986-2f22-43b5-bb24-c83861b8ca7c",
    "name": "6: ADOT",
    "has_children": false,
    "type": "ward"
  },
  {
    "id": "f755b729-5be4-497c-8ad2-d23850443394",
    "name": "7: VELLIKOTH",
    "has_children": false,
    "type": "ward"
  },
  {
    "id": "60c8a0d3-5469-4ff5-89e8-6d361185848e",
    "name": "8: KATTUKULANGARA",
    "has_children": false,
    "type": "ward"
  },
  {
    "id": "edcb22ab-31e4-4bca-8956-fbfc30fc8e6d",
    "name": "9: MAVUNGAL",
    "has_children": false,
    "type": "ward"
  },
  {
    "id": "27523023-9329-4f23-9a32-a3cc43a8d62f",
    "name": "10: RAMNAGAR",
    "has_children": false,
    "type": "ward"
  },
  {
    "id": "a3d016b7-8805-47fa-9264-cc1aba281ff3",
    "name": "11: PALLOT",
    "has_children": false,
    "type": "ward"
  },
  {
    "id": "5d8aa376-0972-4c2d-94a4-2b32f21534b8",
    "name": "12: KIZHAKUMKARA",
    "has_children": false,
    "type": "ward"
  },
  {
    "id": "41fa9547-6df4-4ce8-a9a7-1fe7c5b4f59e",
    "name": "13: THULICHERY",
    "has_children": false,
    "type": "ward"
  },
  {
    "id": "3e444789-1409-42e4-a122-346f63f066ec",
    "name": "14: ATHINHAL",
    "has_children": false,
    "type": "ward"
  },
  {
    "id": "63a31d33-4e59-4d24-a63c-2b68c32d460e",
    "name": "15: ITTAMMAL",
    "has_children": false,
    "type": "ward"
  },
  {
    "id": "77e13dad-8855-482f-a6a2-57d350ee7a6b",
    "name": "16: KOLAVAYAL",
    "has_children": false,
    "type": "ward"
  },
  {
    "id": "8c5b903b-446e-4421-9259-ce6f21671706",
    "name": "17: AJANUR KADAPPURAM",
    "has_children": false,
    "type": "ward"
  },
  {
    "id": "cac18318-2a3c-47eb-be92-777b068d8f21",
    "name": "18: MUTTUMTHALA",
    "has_children": false,
    "type": "ward"
  },
  {
    "id": "c0bb785b-645f-40ef-8dab-b59c4f08bd55",
    "name": "19: MATTUMMAL",
    "has_children": false,
    "type": "ward"
  },
  {
    "id": "5f356395-174d-4962-8041-a19b75c1ee91",
    "name": "20: MALLIKAMAD",
    "has_children": false,
    "type": "ward"
  },
  {
    "id": "6333876a-3376-4a50-bd79-7617f1a7fd7c",
    "name": "21: CHITHARI",
    "has_children": false,
    "type": "ward"
  },
  {
    "id": "b56a33e9-d86b-408b-be4c-168bca85040e",
    "name": "22: BARIKKAD",
    "has_children": false,
    "type": "ward"
  },
  {
    "id": "e29bd52c-a5fc-45aa-be18-ea1d7845abcd",
    "name": "23: MUKKOOD",
    "has_children": false,
    "type": "ward"
  }
]