[
  {
    "id": "080a1c5f-a3b8-4a65-99b2-809174a19f4e",
    "name": "1: PARATHAKKAD",
    "has_children": false,
    "type": "ward"
  },
  {
    "id": "6469e0c8-2a25-4f5a-a160-2c7539392ce9",
    "name": "2: MUTHUPARAMBA",
    "has_children": false,
    "type": "ward"
  },
  {
    "id": "4eed8df3-3f0c-46ee-baaf-c9d5e284d399",
    "name": "3: PEEDIKAKKANDI",
    "has_children": false,
    "type": "ward"
  },
  {
    "id": "5e13d36e-0f6d-4a77-8292-b43e49559ef9",
    "name": "4: MUNDILAKKAL",
    "has_children": false,
    "type": "ward"
  },
  {
    "id": "041c6aa8-65f2-4611-8739-1afa6be3a87d",
    "name": "5: CHULLIKKODE",
    "has_children": false,
    "type": "ward"
  },
  {
    "id": "c191ab08-fca5-4096-8adf-b5b7baecedc7",
    "name": "6: PARAPPUR",
    "has_children": false,
    "type": "ward"
  },
  {
    "id": "5e0a97ca-a440-41e6-bcb7-3b293c63a441",
    "name": "7: VILAYIL",
    "has_children": false,
    "type": "ward"
  },
  {
    "id": "b60a03eb-6509-4c75-a754-bb2f118c8620",
    "name": "8: PANATALUNGAL",
    "has_children": false,
    "type": "ward"
  },
  {
    "id": "79a84556-28a2-4441-af96-1e9ecd51351e",
    "name": "9: VADAKKEPARAMBA",
    "has_children": false,
    "type": "ward"
  },
  {
    "id": "7b2115eb-6755-489a-bdf7-cbe7b68f613a",
    "name": "10: THANIYAMPURAM",
    "has_children": false,
    "type": "ward"
  },
  {
    "id": "7bf5abd1-847a-4954-bae7-f9e3c9b2ae8e",
    "name": "11: MANEERI",
    "has_children": false,
    "type": "ward"
  },
  {
    "id": "53ca9811-b4f8-4323-9264-f1d4885dc922",
    "name": "12: MUTHUVALLOOR",
    "has_children": false,
    "type": "ward"
  },
  {
    "id": "ab95f02d-fdfa-4fb6-b153-591cdc04bbb3",
    "name": "13: PAPPATH",
    "has_children": false,
    "type": "ward"
  },
  {
    "id": "24510e18-af83-4e53-9a56-1ad0286640d8",
    "name": "14: MUNDAKKULAM SOUTH",
    "has_children": false,
    "type": "ward"
  },
  {
    "id": "f3a363b1-c94c-4f78-b119-1746f90f6437",
    "name": "15: MUNDAKKULAM NORTH",
    "has_children": false,
    "type": "ward"
  }
]