[
  {
    "id": "9ba8e340-fadb-4788-b5a3-f536691a5825",
    "name": "1: THRIPRAYAR",
    "has_children": false,
    "type": "ward"
  },
  {
    "id": "69c2e695-c526-481d-ba6f-5af0d7432097",
    "name": "2: THETTALY",
    "has_children": false,
    "type": "ward"
  },
  {
    "id": "2b0fd75d-b9d2-4495-b60c-40b4319a2e0d",
    "name": "3: PRASANNAPURAM",
    "has_children": false,
    "type": "ward"
  },
  {
    "id": "5df9983b-0147-458b-90dd-c54e603cd546",
    "name": "4: EDANAD",
    "has_children": false,
    "type": "ward"
  },
  {
    "id": "5721569e-a768-4aaf-8063-e24ac8ee32e0",
    "name": "5: KALLAYAM",
    "has_children": false,
    "type": "ward"
  },
  {
    "id": "0aab3225-c6ad-4412-baa2-23709e599cdd",
    "name": "6: SREEMOOLANAGARAM NORTH",
    "has_children": false,
    "type": "ward"
  },
  {
    "id": "261cad61-845e-46ec-8e5a-ef3a2b29defb",
    "name": "7: SREEMOOLANAGARAM EAST",
    "has_children": false,
    "type": "ward"
  },
  {
    "id": "da1c0510-d2bc-4092-bd34-a1b13f06ae2a",
    "name": "8: PARATHETTA",
    "has_children": false,
    "type": "ward"
  },
  {
    "id": "d9f86802-8868-4cc7-aade-fbefa3829b81",
    "name": "9: VELLARAPPILLY",
    "has_children": false,
    "type": "ward"
  },
  {
    "id": "ddea4fdd-e403-4e21-b108-2e673f04cd8b",
    "name": "10: THRIKKANIKKAVU",
    "has_children": false,
    "type": "ward"
  },
  {
    "id": "43ac67fc-569e-4f8c-b08a-ba28bc1ee29d",
    "name": "11: SOUTH VELLARAPPILLY",
    "has_children": false,
    "type": "ward"
  },
  {
    "id": "3a906f83-d85a-49d7-a3f1-f91fc3b2879f",
    "name": "12: THIRUVAIRANIKULAM",
    "has_children": false,
    "type": "ward"
  },
  {
    "id": "cc5ca9c2-bd1a-4c6f-9492-5328767c3d43",
    "name": "13: SREEBHOOTHAPURAM EAST",
    "has_children": false,
    "type": "ward"
  },
  {
    "id": "326d4bbb-1cce-48ed-8b0c-06cc0cd945cd",
    "name": "14: SREEBHOOTHAPURAM WEST",
    "has_children": false,
    "type": "ward"
  },
  {
    "id": "14a698f0-6ade-4280-80f1-a4b728abdbb0",
    "name": "15: SREEMOOLANAGARAM SOUTH",
    "has_children": false,
    "type": "ward"
  },
  {
    "id": "187ced4e-3738-4d74-8f30-ea0fb248c216",
    "name": "16: CHOWARA",
    "has_children": false,
    "type": "ward"
  }
]