[
  {
    "id": "d67b950d-b15e-4f1d-906c-9e12e645e4e3",
    "name": "1: PALAPOTTA",
    "has_children": false,
    "type": "ward"
  },
  {
    "id": "94c2e648-59bf-4d49-9b03-b7469d1ffbe5",
    "name": "2: ANIKODE",
    "has_children": false,
    "type": "ward"
  },
  {
    "id": "4f7321c1-a3ef-43f9-bf04-34507dfe1409",
    "name": "3: THACHANKAD",
    "has_children": false,
    "type": "ward"
  },
  {
    "id": "438a905e-d19a-4821-ad3b-2b028ec580af",
    "name": "4: VEESWALAM",
    "has_children": false,
    "type": "ward"
  },
  {
    "id": "09e253ab-77f3-4e1b-851c-eb3115dac23b",
    "name": "5: AMBAD",
    "has_children": false,
    "type": "ward"
  },
  {
    "id": "60280832-1ad2-4d42-85cf-26c095ef7bcf",
    "name": "6: POLLAPADAM",
    "has_children": false,
    "type": "ward"
  },
  {
    "id": "2f3d8ff5-d4c1-437a-a10c-9d2eab272d91",
    "name": "7: PALLANCHATHANUR",
    "has_children": false,
    "type": "ward"
  },
  {
    "id": "8837dd64-e800-4b0a-9026-c45fb7c05c27",
    "name": "8: MANNAM",
    "has_children": false,
    "type": "ward"
  },
  {
    "id": "7ab3416e-87ca-4ec9-8068-663d7baf27ad",
    "name": "9: KIZHAKETHARA",
    "has_children": false,
    "type": "ward"
  },
  {
    "id": "76bb9f11-37e1-4f64-af9c-5643502b9d90",
    "name": "10: CHUNGAMANNAM",
    "has_children": false,
    "type": "ward"
  },
  {
    "id": "1a12d49b-75f7-424a-9533-c2f0078c8789",
    "name": "11: THANNIRANKAD",
    "has_children": false,
    "type": "ward"
  },
  {
    "id": "74078e9f-9edd-41a4-8c52-caf08fb009d5",
    "name": "12: CHATHANKAV",
    "has_children": false,
    "type": "ward"
  },
  {
    "id": "15da48aa-be8a-4199-bf3b-445321d9cc27",
    "name": "13: ERIYANKAD",
    "has_children": false,
    "type": "ward"
  },
  {
    "id": "47fc9b28-469e-4e90-bf5c-4ed2c1e85268",
    "name": "14: CHENGANIYURKAV",
    "has_children": false,
    "type": "ward"
  },
  {
    "id": "a9e0db88-8d7e-4425-9f9b-acff7d9533e1",
    "name": "15: BANGLAW SCHOOL",
    "has_children": false,
    "type": "ward"
  },
  {
    "id": "97c304ec-2072-42c0-8dd7-dd7c1f8312e3",
    "name": "16: MANNAMPULLI",
    "has_children": false,
    "type": "ward"
  }
]