[
  {
    "id": "e4433f47-f565-40d0-bacb-88518dd8bc9b",
    "name": "1: PANAMBUKAD NORTH",
    "has_children": false,
    "type": "ward"
  },
  {
    "id": "36b5d8ab-293a-4c02-a3b3-1073bbfb62cc",
    "name": "2: MULAVUKAD NORTH",
    "has_children": false,
    "type": "ward"
  },
  {
    "id": "3f88b0a7-d228-420f-a7d2-5e8c3838cc40",
    "name": "3: TOWER LINE",
    "has_children": false,
    "type": "ward"
  },
  {
    "id": "0c526270-237b-4cbc-b551-044141a3ca87",
    "name": "4: KERALESWARAPURAM",
    "has_children": false,
    "type": "ward"
  },
  {
    "id": "5f261379-9e0e-4833-bea7-b12738860462",
    "name": "5: VATTEKKATT",
    "has_children": false,
    "type": "ward"
  },
  {
    "id": "4053c301-9ced-4738-8e22-11486f751662",
    "name": "6: ST. MARY'S",
    "has_children": false,
    "type": "ward"
  },
  {
    "id": "c0dcfb5c-6f3e-4b3b-bbf6-a155e5c3d9b2",
    "name": "7: HOSPITAL",
    "has_children": false,
    "type": "ward"
  },
  {
    "id": "e6adec4f-6f30-47d2-91cf-e7828a13084d",
    "name": "8: THANDASSERY",
    "has_children": false,
    "type": "ward"
  },
  {
    "id": "9c612696-0fc7-4153-ad0b-fa6dab204ed9",
    "name": "9: WATER TANK",
    "has_children": false,
    "type": "ward"
  },
  {
    "id": "6f2a1bcf-4731-4657-bdfb-44c0d19f9b67",
    "name": "10: PONNARIMANGALAM",
    "has_children": false,
    "type": "ward"
  },
  {
    "id": "fe4efb7a-7e91-47a0-a2ad-7fb4ea502417",
    "name": "11: PONJIKKARA",
    "has_children": false,
    "type": "ward"
  },
  {
    "id": "b539baed-ba6c-4cee-952c-2dbf9087317f",
    "name": "12: BOLGHATTY",
    "has_children": false,
    "type": "ward"
  },
  {
    "id": "1ced9876-0190-4feb-a741-2e38f66e78a3",
    "name": "13: VALLARPADAM",
    "has_children": false,
    "type": "ward"
  },
  {
    "id": "caa79758-534d-47f3-b524-129f36e92129",
    "name": "14: T. V. CENTRE",
    "has_children": false,
    "type": "ward"
  },
  {
    "id": "7fe53b2c-522d-4bb8-a024-1c7a65f59b50",
    "name": "15: ADIKKANDAM",
    "has_children": false,
    "type": "ward"
  },
  {
    "id": "933bcc4d-300e-4655-ab08-7d8e1a31a64e",
    "name": "16: AMBEDKAR GRAMAM",
    "has_children": false,
    "type": "ward"
  }
]