[
  {
    "id": "42083d56-475b-4ef8-a1ef-74da115af46a",
    "name": "1: RAILWAY STATION",
    "has_children": false,
    "type": "ward"
  },
  {
    "id": "7d302ed2-671e-48fa-bef2-3c1f8f380859",
    "name": "2: CABLE NAGAR",
    "has_children": false,
    "type": "ward"
  },
  {
    "id": "6e113fb1-0002-41b3-a5f7-8ca153aca3b0",
    "name": "3: VAZHACHAL",
    "has_children": false,
    "type": "ward"
  },
  {
    "id": "897e42a4-d4ee-4c08-b1c5-6e9ef4711768",
    "name": "4: PANTHACKAL",
    "has_children": false,
    "type": "ward"
  },
  {
    "id": "bb98f2e3-b783-43bd-b246-0b90e2ff1f68",
    "name": "5: EDAKKUNNU",
    "has_children": false,
    "type": "ward"
  },
  {
    "id": "fd9387b5-ef15-47ca-8326-cbc7b11861a4",
    "name": "6: PALISSERY",
    "has_children": false,
    "type": "ward"
  },
  {
    "id": "5cea5ef0-a33b-4fb2-942e-a7bfbcbcc3cc",
    "name": "7: EZGHATTUMUGHAM",
    "has_children": false,
    "type": "ward"
  },
  {
    "id": "83c58b25-cbcd-46e0-8ac0-c2cc1be5e15c",
    "name": "8: KARAMATTAM",
    "has_children": false,
    "type": "ward"
  },
  {
    "id": "51357986-1322-4d0f-b85e-5be0055884de",
    "name": "9: EDAKKUNNU EAST",
    "has_children": false,
    "type": "ward"
  },
  {
    "id": "fc6026e6-a5fd-4f4e-b52c-6dce303b1cd3",
    "name": "10: PADUVAPURAM",
    "has_children": false,
    "type": "ward"
  },
  {
    "id": "ab87c2ca-6943-40de-a22e-bae2988f4ab3",
    "name": "11: MOONNAMPARAMBU",
    "has_children": false,
    "type": "ward"
  },
  {
    "id": "5e0879ad-4cce-48b5-b07c-35a9c9d3a090",
    "name": "12: MALAYAMKUNNU",
    "has_children": false,
    "type": "ward"
  },
  {
    "id": "4273a8c8-e0c9-4cd8-88ba-5f6b9d62a686",
    "name": "13: PALLIYANGADI",
    "has_children": false,
    "type": "ward"
  },
  {
    "id": "bccdf36b-f514-428b-a8ad-9745bf4fb0a1",
    "name": "14: NJALOOKKARA",
    "has_children": false,
    "type": "ward"
  },
  {
    "id": "565b83f5-2b36-4e19-a222-10dfdfd88ef0",
    "name": "15: KARAYAMPARAMBU EAST",
    "has_children": false,
    "type": "ward"
  },
  {
    "id": "21382bb0-f534-4658-8931-25bce210e7c8",
    "name": "16: KARAYAMPARAMBU WEST",
    "has_children": false,
    "type": "ward"
  },
  {
    "id": "1978cb0b-30ba-4906-9cbb-b2455199c0eb",
    "name": "17: PEECHANIKADU",
    "has_children": false,
    "type": "ward"
  }
]